<batch>
    <label>DE_BIM_CRIF_Extraction</label>
    <description/>
    <type>Extraction</type>
    <category>OIS</category>
    <context>sql extraction</context>
    <filter/>
    <dataSetLabel/>
    <dataPublisherScripts>
        <dataPublisherScript>
            <dapLabel/>
            <directory>Murex</directory>
            <filter/>
            <outputTable>BIM_CRIF_FILE.REP</outputTable>
            <mainTable>Yes</mainTable>
        </dataPublisherScript>
    </dataPublisherScripts>
    <reports/>
    <extractionRequests>
        <extractionRequest>BIM_CRIF_Extraction_2</extractionRequest>
    </extractionRequests>
    <storedProcedures/>
</batch>
